funix/__init__.py
funix/__main__.py
funix/py.typed
funix/app/__init__.py
funix/app/websocket.py
funix/build/.DS_Store
funix/build/asset-manifest.json
funix/build/favicon.ico
funix/build/index.html
funix/build/logo192.png
funix/build/logo512.png
funix/build/manifest.json
funix/build/_images/back.png
funix/build/_images/back_large.png
funix/build/_images/filesave.png
funix/build/_images/filesave_large.png
funix/build/_images/forward.png
funix/build/_images/forward_large.png
funix/build/_images/hand.png
funix/build/_images/help.png
funix/build/_images/help_large.png
funix/build/_images/home.png
funix/build/_images/home_large.png
funix/build/_images/matplotlib.png
funix/build/_images/matplotlib_large.png
funix/build/_images/move.png
funix/build/_images/move_large.png
funix/build/_images/qt4_editor_options.png
funix/build/_images/qt4_editor_options_large.png
funix/build/_images/subplots.png
funix/build/_images/subplots_large.png
funix/build/_images/zoom_to_rect.png
funix/build/_images/zoom_to_rect_large.png
funix/build/static/css/fbm.css
funix/build/static/css/main.8ad5faca.css
funix/build/static/css/mpl.css
funix/build/static/indigo/indigo-ketcher-1.34.0.wasm
funix/build/static/indigo/indigo-ketcher-separate-wasm.js
funix/build/static/js/12.8659166d.chunk.js
funix/build/static/js/124.28ea8ed8.chunk.js
funix/build/static/js/151.4529a321.chunk.js
funix/build/static/js/187.d4c4db68.chunk.js
funix/build/static/js/200.01fbd030.chunk.js
funix/build/static/js/251.c029b5e7.chunk.js
funix/build/static/js/255.82a4cd37.chunk.js
funix/build/static/js/264.dfcca1b2.chunk.js
funix/build/static/js/264.dfcca1b2.chunk.js.LICENSE.txt
funix/build/static/js/266.ddf680d4.chunk.js
funix/build/static/js/278.ff0b397c.chunk.js
funix/build/static/js/291.43d8d2dc.chunk.js
funix/build/static/js/31.5ed5a1ef.chunk.js
funix/build/static/js/341.9f90c43a.chunk.js
funix/build/static/js/341.9f90c43a.chunk.js.LICENSE.txt
funix/build/static/js/403.94421e90.chunk.js
funix-0.6.4.dist-info/licenses/LICENSE
funix-0.6.4.dist-info/METADATA
funix-0.6.4.dist-info/WHEEL
funix-0.6.4.dist-info/entry_points.txt
funix-0.6.4.dist-info/top_level.txt
funix-0.6.4.dist-info/RECORD
