Metadata-Version: 2.4
Name: funix
Version: 0.6.4
Summary: Building web apps without manually creating widgets
Author-email: "Textea Inc." <forrestbao@gmail.com>
License: MIT License
Project-URL: homepage, https://github.com/TexteaInc/funix
Classifier: Development Status :: 4 - Beta
Classifier: License :: OSI Approved :: MIT License
Classifier: Programming Language :: Python :: 3.10
Classifier: Programming Language :: Python :: 3.11
Classifier: Operating System :: OS Independent
Classifier: Framework :: Flask
Classifier: Framework :: Matplotlib
Requires-Python: >=3.10
License-File: LICENSE
Requires-Dist: flask>=2.2.2
Requires-Dist: functions-framework==3.*
Requires-Dist: requests>=2.28.1
Requires-Dist: plac>=1.3.5
Requires-Dist: gitignore-parser>=0.1.9
Requires-Dist: flask-sock>=0.7.0
Requires-Dist: SQLAlchemy>=2.0.23
Requires-Dist: matplotlib>=3.4.3
Requires-Dist: pandas>=2.0.3
Requires-Dist: docstring_parser>=0.16
Requires-Dist: tornado>=6.4.2
Requires-Dist: pydantic>=2.10.6
Requires-Dist: GitPython>=3.1.31
Provides-Extra: pendera
Requires-Dist: pandera>=0.17.2; extra == "pendera"
Provides-Extra: ipython
Requires-Dist: IPython>=8.14.0; extra == "ipython"
Requires-Dist: ipywidgets>=8.0.7; extra == "ipython"
Provides-Extra: all
Requires-Dist: IPython>=8.14.0; extra == "all"
Requires-Dist: ipywidgets>=8.0.7; extra == "all"
Requires-Dist: pandera>=0.17.2; extra == "all"
Dynamic: license-file
